rbadata/__init__.py
rbadata/alerts.py
rbadata/async_core.py
rbadata/benchmarks.py
rbadata/browse.py
rbadata/cache.py
rbadata/calculator.py
rbadata/cash_rate.py
rbadata/chart_pack.py
rbadata/config.py
rbadata/core.py
rbadata/csv_parser.py
rbadata/data.py
rbadata/download.py
rbadata/exceptions.py
rbadata/fetcher.py
rbadata/forecasts.py
rbadata/glossary.py
rbadata/snapshots.py
rbadata/standardize.py
rbadata/tidy.py
rbadata/utils.py
rbadata/web_scraper.py
rbadata/data/series_list.json
rbadata/data/series_metadata.json
rbadata/data/table_list.json
rbadata/examples/01_basic_usage.py
rbadata/examples/02_data_browsing.py
rbadata/examples/03_forecasts.py
rbadata/examples/04_inflation_calculator.py
rbadata/examples/05_chart_pack.py
rbadata/examples/06_snapshots.py
rbadata/examples/07_alerts.py
rbadata/examples/08_glossary.py
rbadata/examples/09_advanced_usage.py
rbadata/examples/10_data_analysis.py
rbadata/examples/README.md
rbadata-0.1.5.dist-info/licenses/LICENSE
rbadata-0.1.5.dist-info/METADATA
rbadata-0.1.5.dist-info/WHEEL
rbadata-0.1.5.dist-info/top_level.txt
rbadata-0.1.5.dist-info/RECORD
