Metadata-Version: 2.4
Name: rbadata
Version: 0.1.5
Summary: Download and tidy data from the Reserve Bank of Australia
Author: caymandev
Maintainer: caymandev
License: MIT
Project-URL: Homepage, https://github.com/caymandev/rbadata
Project-URL: Documentation, https://rbadata.readthedocs.io
Project-URL: Repository, https://github.com/caymandev/rbadata
Project-URL: Issues, https://github.com/caymandev/rbadata/issues
Keywords: rba,economics,finance,australia,data
Classifier: Development Status :: 3 - Alpha
Classifier: Intended Audience :: Science/Research
Classifier: License :: OSI Approved :: MIT License
Classifier: Programming Language :: Python :: 3
Classifier: Programming Language :: Python :: 3.9
Classifier: Programming Language :: Python :: 3.10
Classifier: Programming Language :: Python :: 3.11
Classifier: Programming Language :: Python :: 3.12
Requires-Python: >=3.9
License-File: LICENSE
Requires-Dist: pandas>=1.3.0
Requires-Dist: requests>=2.25.0
Requires-Dist: openpyxl>=3.0.0
Requires-Dist: beautifulsoup4>=4.9.0
Requires-Dist: lxml>=4.6.0
Requires-Dist: python-dateutil>=2.8.0
Requires-Dist: aiohttp>=3.8.0
Provides-Extra: dev
Requires-Dist: pytest>=6.0; extra == "dev"
Requires-Dist: pytest-cov>=2.0; extra == "dev"
Requires-Dist: pytest-asyncio>=0.21.0; extra == "dev"
Requires-Dist: black>=22.0; extra == "dev"
Requires-Dist: flake8>=4.0; extra == "dev"
Requires-Dist: mypy>=0.900; extra == "dev"
Requires-Dist: isort>=5.0; extra == "dev"
Requires-Dist: bump2version>=1.0.1; extra == "dev"
Dynamic: license-file
